LICENSE
README.md
pyproject.toml
requirements-dev.txt
requirements-extras.txt
requirements.txt
setup.py
docs/requirements.txt
src/pyoutil/__init__.py
src/torchoutil/__init__.py
src/torchoutil/__main__.py
src/torchoutil/entries.py
src/torchoutil/info.py
src/torchoutil.egg-info/PKG-INFO
src/torchoutil.egg-info/SOURCES.txt
src/torchoutil.egg-info/dependency_links.txt
src/torchoutil.egg-info/entry_points.txt
src/torchoutil.egg-info/requires.txt
src/torchoutil.egg-info/top_level.txt
src/torchoutil/core/__init__.py
src/torchoutil/core/dtype_enum.py
src/torchoutil/core/get.py
src/torchoutil/core/make.py
src/torchoutil/core/packaging.py
src/torchoutil/core/semver.py
src/torchoutil/core/version.py
src/torchoutil/extras/__init__.py
src/torchoutil/extras/colorlog.py
src/torchoutil/extras/safetensors.py
src/torchoutil/extras/tensorboard.py
src/torchoutil/extras/torchaudio.py
src/torchoutil/extras/yaml.py
src/torchoutil/extras/hdf/__init__.py
src/torchoutil/extras/hdf/common.py
src/torchoutil/extras/hdf/dataset.py
src/torchoutil/extras/hdf/pack.py
src/torchoutil/extras/numpy/__init__.py
src/torchoutil/extras/numpy/_numpy_fallback.py
src/torchoutil/extras/numpy/definitions.py
src/torchoutil/extras/numpy/functional.py
src/torchoutil/extras/numpy/modules.py
src/torchoutil/extras/numpy/saving.py
src/torchoutil/extras/numpy/scan_info.py
src/torchoutil/hub/__init__.py
src/torchoutil/hub/download.py
src/torchoutil/hub/paths.py
src/torchoutil/hub/registry.py
src/torchoutil/nn/__init__.py
src/torchoutil/nn/functional/__init__.py
src/torchoutil/nn/functional/activation.py
src/torchoutil/nn/functional/checksum.py
src/torchoutil/nn/functional/cropping.py
src/torchoutil/nn/functional/get.py
src/torchoutil/nn/functional/indices.py
src/torchoutil/nn/functional/make.py
src/torchoutil/nn/functional/mask.py
src/torchoutil/nn/functional/multiclass.py
src/torchoutil/nn/functional/multilabel.py
src/torchoutil/nn/functional/new.py
src/torchoutil/nn/functional/numpy.py
src/torchoutil/nn/functional/others.py
src/torchoutil/nn/functional/padding.py
src/torchoutil/nn/functional/powerset.py
src/torchoutil/nn/functional/predicate.py
src/torchoutil/nn/functional/segments.py
src/torchoutil/nn/functional/transform.py
