Metadata-Version: 2.4
Name: torchoutil
Version: 0.6.1
Summary: Collection of functions and modules to help development in PyTorch.
Author-email: "Étienne Labbé (Labbeti)" <labbeti.pub@gmail.com>
Maintainer-email: "Étienne Labbé (Labbeti)" <labbeti.pub@gmail.com>
License: MIT License
Project-URL: Homepage, https://pypi.org/project/torchoutil/
Project-URL: Documentation, https://torchoutil.readthedocs.io/
Project-URL: Repository, https://github.com/Labbeti/torchoutil.git
Project-URL: Changelog, https://github.com/Labbeti/torchoutil/blob/main/CHANGELOG.md
Project-URL: Tracker, https://github.com/Labbeti/torchoutil/issues
Keywords: pytorch,deep-learning
Classifier: Intended Audience :: Developers
Classifier: Intended Audience :: Science/Research
Classifier: License :: OSI Approved :: MIT License
Classifier: Programming Language :: Python :: 3
Classifier: Programming Language :: Python :: 3.8
Classifier: Programming Language :: Python :: 3.9
Classifier: Programming Language :: Python :: 3.10
Classifier: Programming Language :: Python :: 3.11
Classifier: Programming Language :: Python :: 3.12
Classifier: Programming Language :: Python :: 3.13
Classifier: Topic :: Scientific/Engineering
Classifier: Topic :: Scientific/Engineering :: Artificial Intelligence
Classifier: Operating System :: OS Independent
Requires-Python: >=3.8
License-File: LICENSE
Requires-Dist: torch>=1.10.0
Requires-Dist: typing_extensions>=4.10.0
Provides-Extra: extras
Requires-Dist: colorlog; extra == "extras"
Requires-Dist: h5py; extra == "extras"
Requires-Dist: numpy; extra == "extras"
Requires-Dist: omegaconf; extra == "extras"
Requires-Dist: pandas; extra == "extras"
Requires-Dist: pyyaml; extra == "extras"
Requires-Dist: safetensors; extra == "extras"
Requires-Dist: scipy; extra == "extras"
Requires-Dist: tensorboard; extra == "extras"
Requires-Dist: torchaudio>=0.10.0; extra == "extras"
Requires-Dist: tqdm; extra == "extras"
Provides-Extra: dev
Requires-Dist: black==23.12.1; extra == "dev"
Requires-Dist: coverage[toml]; extra == "dev"
Requires-Dist: flake8; extra == "dev"
Requires-Dist: ipython; extra == "dev"
Requires-Dist: pre-commit; extra == "dev"
Requires-Dist: pytest; extra == "dev"
Requires-Dist: soundfile; extra == "dev"
Requires-Dist: sphinx; extra == "dev"
Requires-Dist: sphinx-press-theme>=0.8.0; extra == "dev"
Requires-Dist: torchaudio>=0.10.0; extra == "dev"
Requires-Dist: torchvision>=0.11.0; extra == "dev"
Requires-Dist: twine; extra == "dev"
Requires-Dist: sphinx-press-theme>=0.8.0; extra == "dev"
Dynamic: license-file
